pyEDAA/UCIS/Cobertura.py
pyEDAA/UCIS/UCDB.py
pyEDAA/UCIS/__init__.py
pyEDAA/UCIS/CLI/__init__.py
pyEDAA.UCIS-0.3.0.dist-info/LICENSE.md
pyEDAA.UCIS-0.3.0.dist-info/METADATA
pyEDAA.UCIS-0.3.0.dist-info/WHEEL
pyEDAA.UCIS-0.3.0.dist-info/entry_points.txt
pyEDAA.UCIS-0.3.0.dist-info/top_level.txt
pyEDAA.UCIS-0.3.0.dist-info/RECORD
