Metadata-Version: 2.1
Name: pyEDAA.UCIS
Version: 0.3.0
Summary: Tools to extract and convert data from UCDB files.
Home-page: https://GitHub.com/pyEDAA/pyEDAA.UCIS
Author: Patrick Lehmann
Author-email: Paebbels@gmail.com
License: Apache-2.0
Project-URL: Documentation, https://pyEDAA.GitHub.io/pyEDAA.UCIS
Project-URL: Source Code, https://GitHub.com/pyEDAA/pyEDAA.UCIS
Project-URL: Issue Tracker, https://GitHub.com/pyEDAA/pyEDAA.UCIS/issues
Keywords: UCIS,UCDB,coverage,Cobertura,xml
Platform: UNKNOWN
Classifier: Topic :: Scientific/Engineering :: Electronic Design Automation (EDA)
Classifier: License :: OSI Approved :: Apache Software License
Classifier: Programming Language :: Python :: 3 :: Only
Classifier: Programming Language :: Python :: 3.7
Classifier: Programming Language :: Python :: 3.8
Classifier: Programming Language :: Python :: 3.9
Classifier: Programming Language :: Python :: 3.10
Classifier: Development Status :: 5 - Production/Stable
Requires-Python: >=3.7
License-File: LICENSE.md
Requires-Dist: pyTooling (>=1.9.5)
Requires-Dist: lxml (>=4.8)
Requires-Dist: pyAttributes (>=2.5.1)
Provides-Extra: all
Requires-Dist: sphinx (>=4.4.0) ; extra == 'all'
Requires-Dist: lxml (>=4.8) ; extra == 'all'
Requires-Dist: sphinxcontrib-mermaid (>=0.7.1) ; extra == 'all'
Requires-Dist: pyAttributes (>=2.5.1) ; extra == 'all'
Requires-Dist: sphinxcontrib.autoprogram (>=0.1.7) ; extra == 'all'
Requires-Dist: autoapi (>=2.0.1) ; extra == 'all'
Requires-Dist: pyTooling (>=1.9.5) ; extra == 'all'
Requires-Dist: sphinx-fontawesome (>=0.0.6) ; extra == 'all'
Requires-Dist: sphinx-autodoc-typehints (>=1.17.0) ; extra == 'all'
Provides-Extra: doc
Requires-Dist: sphinx (>=4.4.0) ; extra == 'doc'
Requires-Dist: sphinx-fontawesome (>=0.0.6) ; extra == 'doc'
Requires-Dist: sphinxcontrib-mermaid (>=0.7.1) ; extra == 'doc'
Requires-Dist: pyAttributes (>=2.5.1) ; extra == 'doc'
Requires-Dist: sphinxcontrib.autoprogram (>=0.1.7) ; extra == 'doc'
Requires-Dist: autoapi (>=2.0.1) ; extra == 'doc'
Requires-Dist: pyTooling (>=1.9.5) ; extra == 'doc'
Requires-Dist: lxml (>=4.8) ; extra == 'doc'
Requires-Dist: sphinx-autodoc-typehints (>=1.17.0) ; extra == 'doc'
